{"assets/fonts/Raleway/Raleway-Bold.ttf":["assets/fonts/Raleway/Raleway-Bold.ttf"],"assets/fonts/Raleway/Raleway-Italic.ttf":["assets/fonts/Raleway/Raleway-Italic.ttf"],"assets/fonts/Raleway/Raleway-Light.ttf":["assets/fonts/Raleway/Raleway-Light.ttf"],"assets/fonts/Raleway/Raleway-Regular.ttf":["assets/fonts/Raleway/Raleway-Regular.ttf"],"assets/images/facebook.png":["assets/images/facebook.png"],"assets/images/instagram.png":["assets/images/instagram.png"],"assets/images/logo.png":["assets/images/logo.png"],"assets/images/main.png":["assets/images/main.png"],"assets/images/mission1.webp":["assets/images/mission1.webp"],"assets/images/mission2.webp":["assets/images/mission2.webp"],"assets/images/mission3.webp":["assets/images/mission3.webp"],"assets/images/mission4.webp":["assets/images/mission4.webp"],"assets/images/mission5.webp":["assets/images/mission5.webp"],"assets/images/mission6.webp":["assets/images/mission6.webp"],"assets/images/mission7.webp":["assets/images/mission7.webp"],"assets/images/mission8.webp":["assets/images/mission8.webp"],"assets/images/mission9.webp":["assets/images/mission9.webp"],"assets/images/textStroke.png":["assets/images/textStroke.png"],"assets/images/twitter.png":["assets/images/twitter.png"],"assets/images/working1.png":["assets/images/working1.png"],"assets/images/working2.png":["assets/images/working2.png"],"assets/images/working3.png":["assets/images/working3.png"],"assets/images/youtube.png":["assets/images/youtube.png"],"packages/cupertino_icons/assets/CupertinoIcons.ttf":["packages/cupertino_icons/assets/CupertinoIcons.ttf"]}